bigleaf/WUE_metrics.py
bigleaf/__init__.py
bigleaf/aerodynamic_conductance.py
bigleaf/bigleaf_constants.py
bigleaf/bigleaf_physiology.py
bigleaf/boundary_layer_conductance.py
bigleaf/check_input.py
bigleaf/datasets_description.py
bigleaf/decoupling.py
bigleaf/energy_balance.py
bigleaf/evapotranspiration.py
bigleaf/filter_data.py
bigleaf/meteorological_variables.py
bigleaf/optimum_temperature.py
bigleaf/potential_radiation.py
bigleaf/stability_correction.py
bigleaf/surface_conditions.py
bigleaf/surface_conductance.py
bigleaf/surface_roughness.py
bigleaf/unit_conversions.py
bigleaf-0.0.2.dist-info/LICENSE
bigleaf-0.0.2.dist-info/METADATA
bigleaf-0.0.2.dist-info/WHEEL
bigleaf-0.0.2.dist-info/top_level.txt
bigleaf-0.0.2.dist-info/RECORD
